ostream/__init__.py
ostream-0.0.1.dist-info/METADATA
ostream-0.0.1.dist-info/WHEEL
ostream-0.0.1.dist-info/top_level.txt
ostream-0.0.1.dist-info/RECORD
