Metadata-Version: 2.1
Name: ostream
Version: 0.0.1
Summary: Object storage streams for python
Author-email: Alex Kwiatkowski <alex+pypi@fremantle.io>
License: MIT License
Project-URL: Homepage, https://github.com/rupurt/ostream
Project-URL: Issues, https://github.com/rupurt/ostream/issues
Classifier: Programming Language :: Python :: 3
Classifier: Operating System :: OS Independent
Requires-Python: >=3.12
Requires-Dist: obstore >=0.5.0
